[
  {
    "product": [
      {
        "id": 1,
        "slug": "/tour-turkmenistan-highlights",
        "title": "Turkmenistan Highlights Tour",
        "short_des": "Ashgabat, Darvaza Gas Crater, Ancient Merv and desert landscapes.",
        "description": "",
        "image": "/assets/images/special-offers-img1.jpg",
        "alt": "Turkmenistan Highlights Tour",
        "date": "Private",
        "day": 7,
        "rating": "4.9",
        "price": 850,
        "old_price": 0
      },
      {
        "id": 2,
        "slug": "/tour-uzbekistan-silk-road",
        "title": "Uzbekistan Silk Road Classic",
        "short_des": "Samarkand, Bukhara, Khiva and Tashkent in one classic cultural route.",
        "description": "",
        "image": "/assets/images/special-offers-img2.jpg",
        "alt": "Uzbekistan Silk Road Classic",
        "date": "Private",
        "day": 8,
        "rating": "5.0",
        "price": 980,
        "old_price": 0
      },
      {
        "id": 3,
        "slug": "/tour-five-stans",
        "title": "Five Stans Central Asia Tour",
        "short_des": "A complete journey across Turkmenistan, Uzbekistan, Tajikistan, Kyrgyzstan and Kazakhstan.",
        "description": "",
        "image": "/assets/images/special-offers-img3.jpg",
        "alt": "Five Stans Central Asia Tour",
        "date": "Group",
        "day": 15,
        "rating": "4.9",
        "price": 2950,
        "old_price": 0
      },
      {
        "id": 4,
        "slug": "/tour-uzbekistan-turkmenistan",
        "title": "Uzbekistan & Turkmenistan Tour",
        "short_des": "Silk Road cities, desert routes, Ashgabat, Ancient Merv and Darvaza.",
        "description": "",
        "image": "/assets/images/popular-tours-img7.jpg",
        "alt": "Uzbekistan and Turkmenistan Tour",
        "date": "Private",
        "day": 12,
        "rating": "4.8",
        "price": 1680,
        "old_price": 0
      },
      {
        "id": 5,
        "slug": "/tour-kyrgyzstan-mountain-lake",
        "title": "Kyrgyzstan Nomad Adventure",
        "short_des": "Yurt camps, mountain lakes, open roads and nomad culture.",
        "description": "",
        "image": "/assets/images/popular-tours-img5.jpg",
        "alt": "Kyrgyzstan Nomad Adventure",
        "date": "Private",
        "day": 8,
        "rating": "4.9",
        "price": 920,
        "old_price": 0
      },
      {
        "id": 6,
        "slug": "/tour-kazakhstan-kyrgyzstan",
        "title": "Kazakhstan & Kyrgyzstan Tour",
        "short_des": "Almaty, Charyn Canyon, Issyk-Kul, Karakol and alpine valleys.",
        "description": "",
        "image": "/assets/images/top-destinations-img-2.jpg",
        "alt": "Kazakhstan and Kyrgyzstan Tour",
        "date": "Private",
        "day": 10,
        "rating": "4.8",
        "price": 1250,
        "old_price": 0
      },
      {
        "id": 7,
        "slug": "/tour-pamir-highway",
        "title": "Tajikistan Pamir Highway Tour",
        "short_des": "A high mountain journey through the Pamirs, valleys and remote villages.",
        "description": "",
        "image": "/assets/images/popular-tours-img10.jpg",
        "alt": "Tajikistan Pamir Highway Tour",
        "date": "Private",
        "day": 11,
        "rating": "4.9",
        "price": 1450,
        "old_price": 0
      },
      {
        "id": 8,
        "slug": "/tour-detail",
        "title": "Darvaza Gas Crater Overnight Tour",
        "short_des": "A short desert escape to the Gates of Hell with camping under the stars.",
        "description": "",
        "image": "/assets/images/popular-tours-img8.jpg",
        "alt": "Darvaza Gas Crater Overnight Tour",
        "date": "Private",
        "day": 2,
        "rating": "4.8",
        "price": 280,
        "old_price": 0
      },
      {
        "id": 9,
        "slug": "/tour-detail",
        "title": "Ancient Merv & Ashgabat Tour",
        "short_des": "Explore Ashgabat, UNESCO-listed Ancient Merv and Silk Road history.",
        "description": "",
        "image": "/assets/images/popular-tours-img11.jpg",
        "alt": "Ancient Merv and Ashgabat Tour",
        "date": "Private",
        "day": 5,
        "rating": "4.7",
        "price": 620,
        "old_price": 0
      }
    ]
  }
]